{
  "unit": "g12dn-unit4",
  "unit_title": "The next step",
  "theme": "жЬ™жЭ•иІДеИТ",
  "vocabulary": [
    {
      "word_id": "g12dn_unit4_001",
      "word": "transition",
      "meaning": "ињЗжЄ°",
      "part_of_speech": "noun",
      "phrase": [
        "smooth transition",
        "make the transition"
      ],
      "sentence": "The transition from school to work is challenging.",
      "phonetic": "/tr√¶nЋИz…™ Гn/",
      "error_tags": [
        "жЛЉеЖЩйФЩ"
      ]
    },
    {
      "word_id": "g12dn_unit4_002",
      "word": "graduation",
      "meaning": "жѓХдЄЪ",
      "part_of_speech": "noun",
      "phrase": [
        "after graduation",
        "graduation ceremony"
      ],
      "sentence": "After graduation, I want to travel.",
      "phonetic": "/ЋМ…°r√¶d ТuЋИe…™ Гn/",
      "error_tags": [
        "жЛЉеЖЩйФЩ"
      ]
    },
    {
      "word_id": "g12dn_unit4_003",
      "word": "gap year",
      "meaning": "йЧійЪФеєі",
      "part_of_speech": "noun",
      "phrase": [
        "take a gap year",
        "during my gap year"
      ],
      "sentence": "She took a gap year to travel.",
      "phonetic": "",
      "error_tags": [
        "жЛЉеЖЩйФЩ"
      ]
    },
    {
      "word_id": "g12dn_unit4_004",
      "word": "undergraduate",
      "meaning": "жЬђзІСзФЯ",
      "part_of_speech": "noun",
      "phrase": [
        "undergraduate student",
        "undergraduate degree"
      ],
      "sentence": "He is an undergraduate at Peking University.",
      "phonetic": "/ЋМ Мnd…ЩrЋИ…°r√¶d Тu…Щt/",
      "error_tags": [
        "жЛЉеЖЩйФЩ"
      ]
    },
    {
      "word_id": "g12dn_unit4_005",
      "word": "postgraduate",
      "meaning": "з†Фз©ґзФЯ",
      "part_of_speech": "noun",
      "phrase": [
        "postgraduate study",
        "postgraduate degree"
      ],
      "sentence": "She is doing postgraduate research.",
      "phonetic": "/ЋМp…Щ КstЋИ…°r√¶d Тu…Щt/",
      "error_tags": [
        "жЛЉеЖЩйФЩ"
      ]
    },
    {
      "word_id": "g12dn_unit4_006",
      "word": "scholarship",
      "meaning": "е•Це≠¶йЗС",
      "part_of_speech": "noun",
      "phrase": [
        "full scholarship",
        "apply for a scholarship"
      ],
      "sentence": "She won a scholarship to study abroad.",
      "phonetic": "/ЋИsk…Тl…Щr Г…™p/",
      "error_tags": [
        "жЛЉеЖЩйФЩ"
      ]
    },
    {
      "word_id": "g12dn_unit4_007",
      "word": "tuition",
      "meaning": "е≠¶иіє",
      "part_of_speech": "noun",
      "phrase": [
        "tuition fees",
        "pay tuition"
      ],
      "sentence": "The tuition is quite expensive.",
      "phonetic": "/tjuЋРЋИ…™ Гn/",
      "error_tags": [
        "жЛЉеЖЩйФЩ"
      ]
    },
    {
      "word_id": "g12dn_unit4_008",
      "word": "accommodation",
      "meaning": "дљПеЃњ",
      "part_of_speech": "noun",
      "phrase": [
        "student accommodation",
        "find accommodation"
      ],
      "sentence": "University accommodation is often on campus.",
      "phonetic": "/…ЩЋМk…Тm…ЩЋИde…™ Гn/",
      "error_tags": [
        "жЛЉеЖЩйФЩ"
      ]
    },
    {
      "word_id": "g12dn_unit4_009",
      "word": "campus",
      "meaning": "ж†°еЫ≠",
      "part_of_speech": "noun",
      "phrase": [
        "on campus",
        "campus life"
      ],
      "sentence": "Campus life is exciting and diverse.",
      "phonetic": "/ЋИk√¶mp…Щs/",
      "error_tags": [
        "жЛЉеЖЩйФЩ"
      ]
    },
    {
      "word_id": "g12dn_unit4_010",
      "word": "freshman",
      "meaning": "е§ІдЄАжЦ∞зФЯ",
      "part_of_speech": "noun",
      "phrase": [
        "freshman year",
        "college freshman"
      ],
      "sentence": "Freshman year is full of new experiences.",
      "phonetic": "/ЋИfre Гm…Щn/",
      "error_tags": [
        "жЛЉеЖЩйФЩ"
      ]
    },
    {
      "word_id": "g12dn_unit4_011",
      "word": "sophomore",
      "meaning": "е§ІдЇМе≠¶зФЯ",
      "part_of_speech": "noun",
      "phrase": [
        "sophomore year",
        "sophomore student"
      ],
      "sentence": "By sophomore year, you know your way around.",
      "phonetic": "/ЋИs…Тf…Щm…ФЋРr/",
      "error_tags": [
        "жЛЉеЖЩйФЩ"
      ]
    },
    {
      "word_id": "g12dn_unit4_012",
      "word": "seminar",
      "meaning": "з†ФиЃ®дЉЪ",
      "part_of_speech": "noun",
      "phrase": [
        "attend a seminar",
        "give a seminar"
      ],
      "sentence": "The seminar on career planning was helpful.",
      "phonetic": "/ЋИsem…™n…СЋРr/",
      "error_tags": [
        "жЛЉеЖЩйФЩ"
      ]
    },
    {
      "word_id": "g12dn_unit4_013",
      "word": "thesis",
      "meaning": "иЃЇжЦЗ",
      "part_of_speech": "noun",
      "phrase": [
        "write a thesis",
        "master's thesis"
      ],
      "sentence": "I spent six months writing my thesis.",
      "phonetic": "/ЋИќЄiЋРs…™s/",
      "error_tags": [
        "жЛЉеЖЩйФЩ"
      ]
    },
    {
      "word_id": "g12dn_unit4_014",
      "word": "dissertation",
      "meaning": "жѓХдЄЪиЃЇжЦЗ",
      "part_of_speech": "noun",
      "phrase": [
        "doctoral dissertation",
        "defend a dissertation"
      ],
      "sentence": "She is working on her dissertation.",
      "phonetic": "/ЋМd…™s…ЩrЋИte…™ Гn/",
      "error_tags": [
        "жЛЉеЖЩйФЩ"
      ]
    },
    {
      "word_id": "g12dn_unit4_015",
      "word": "volunteer",
      "meaning": "ењЧжДњиАЕ",
      "part_of_speech": "noun",
      "phrase": [
        "volunteer work",
        "become a volunteer"
      ],
      "sentence": "Volunteering looks good on your resume.",
      "phonetic": "/ЋМv…Тl…ЩnЋИt…™…Щr/",
      "error_tags": [
        "жЛЉеЖЩйФЩ"
      ]
    },
    {
      "word_id": "g12dn_unit4_016",
      "word": "intern",
      "meaning": "еЃЮдє†зФЯ",
      "part_of_speech": "noun",
      "phrase": [
        "summer intern",
        "engineering intern"
      ],
      "sentence": "I worked as an intern at a tech company.",
      "phonetic": "/ЋИ…™nt…ЬЋРrn/",
      "error_tags": [
        "жЛЉеЖЩйФЩ"
      ]
    },
    {
      "word_id": "g12dn_unit4_017",
      "word": "apprenticeship",
      "meaning": "е≠¶еЊТжЬЯ",
      "part_of_speech": "noun",
      "phrase": [
        "start an apprenticeship",
        "complete an apprenticeship"
      ],
      "sentence": "An apprenticeship combines work and study.",
      "phonetic": "/…ЩЋИprent…™s Г…™p/",
      "error_tags": [
        "жЛЉеЖЩйФЩ"
      ]
    },
    {
      "word_id": "g12dn_unit4_018",
      "word": "vocational",
      "meaning": "иБМдЄЪзЪД",
      "part_of_speech": "adj",
      "phrase": [
        "vocational training",
        "vocational school"
      ],
      "sentence": "Vocational schools teach practical skills.",
      "phonetic": "/v…Щ КЋИke…™ Г…Щnl/",
      "error_tags": [
        "жЛЉеЖЩйФЩ"
      ]
    },
    {
      "word_id": "g12dn_unit4_019",
      "word": "lifelong learning",
      "meaning": "зїИиЇЂе≠¶дє†",
      "part_of_speech": "noun",
      "phrase": [
        "embrace lifelong learning",
        "lifelong learning habit"
      ],
      "sentence": "Lifelong learning keeps your skills up to date.",
      "phonetic": "",
      "error_tags": [
        "жЛЉеЖЩйФЩ"
      ]
    },
    {
      "word_id": "g12dn_unit4_020",
      "word": "self-improvement",
      "meaning": "иЗ™жИСжПРеНЗ",
      "part_of_speech": "noun",
      "phrase": [
        "continuous self-improvement",
        "focus on self-improvement"
      ],
      "sentence": "Self-improvement is a lifelong journey.",
      "phonetic": "",
      "error_tags": [
        "жЛЉеЖЩйФЩ"
      ]
    },
    {
      "word_id": "g12dn_unit4_021",
      "word": "adaptability",
      "meaning": "йАВеЇФиГљеКЫ",
      "part_of_speech": "noun",
      "phrase": [
        "show adaptability",
        "key adaptability"
      ],
      "sentence": "Adaptability is crucial in a fast-changing world.",
      "phonetic": "/…ЩЋМd√¶pt…ЩЋИb…™l…Щti/",
      "error_tags": [
        "жЛЉеЖЩйФЩ"
      ]
    },
    {
      "word_id": "g12dn_unit4_022",
      "word": "entrepreneurship",
      "meaning": "еИЫдЄЪз≤Њз•Ю",
      "part_of_speech": "noun",
      "phrase": [
        "encourage entrepreneurship",
        "social entrepreneurship"
      ],
      "sentence": "Entrepreneurship can create new opportunities.",
      "phonetic": "/ЋМ…Тntr…Щpr…ЩЋИn…ЬЋРr Г…™p/",
      "error_tags": [
        "жЛЉеЖЩйФЩ"
      ]
    },
    {
      "word_id": "g12dn_unit4_023",
      "word": "potential",
      "meaning": "жљЬеКЫ",
      "part_of_speech": "noun",
      "phrase": [
        "reach your potential",
        "full potential"
      ],
      "sentence": "Everyone has great potential.",
      "phonetic": "/p…ЩЋИten Гl/",
      "error_tags": [
        "жЛЉеЖЩйФЩ"
      ]
    },
    {
      "word_id": "g12dn_unit4_024",
      "word": "aspiration",
      "meaning": "ењЧеРС",
      "part_of_speech": "noun",
      "phrase": [
        "career aspiration",
        "high aspiration"
      ],
      "sentence": "Follow your aspirations and dreams.",
      "phonetic": "/ЋМ√¶sp…ЩЋИre…™ Гn/",
      "error_tags": [
        "жЛЉеЖЩйФЩ"
      ]
    },
    {
      "word_id": "g12dn_unit4_025",
      "word": "destiny",
      "meaning": "еСљињР",
      "part_of_speech": "noun",
      "phrase": [
        "control your destiny",
        "meet your destiny"
      ],
      "sentence": "Your destiny is in your own hands.",
      "phonetic": "/ЋИdest…Щni/",
      "error_tags": [
        "жЛЉеЖЩйФЩ"
      ]
    }
  ]
}